genomicranges/GenomicRanges.py
genomicranges/__init__.py
genomicranges/grangeslist.py
genomicranges/sequence_info.py
genomicranges/utils.py
genomicranges/io/__init__.py
genomicranges/io/gtf.py
genomicranges/io/ucsc.py
genomicranges-0.8.4.dist-info/licenses/LICENSE.txt
genomicranges-0.8.4.dist-info/METADATA
genomicranges-0.8.4.dist-info/WHEEL
genomicranges-0.8.4.dist-info/top_level.txt
genomicranges-0.8.4.dist-info/RECORD
