Metadata-Version: 2.4
Name: GenomicRanges
Version: 0.8.4
Summary: Container class to represent and operate over genomic regions and annotations.
Home-page: https://github.com/BiocPy/GenomicRanges
Author: Jayaram Kancherla
Author-email: jayaram.kancherla@gmail.com
License: MIT
Project-URL: Documentation, https://github.com/BiocPy/GenomicRanges
Platform: any
Classifier: Development Status :: 4 - Beta
Classifier: Programming Language :: Python
Requires-Python: >=3.9
License-File: LICENSE.txt
Requires-Dist: importlib-metadata; python_version < "3.8"
Requires-Dist: biocframe>=0.7.1
Requires-Dist: iranges>=0.7.2
Requires-Dist: biocutils>=0.3.3
Requires-Dist: compressed_lists>=0.4.3
Requires-Dist: numpy
Provides-Extra: optional
Requires-Dist: joblib; extra == "optional"
Requires-Dist: pandas; extra == "optional"
Requires-Dist: polars; extra == "optional"
Requires-Dist: matplotlib; extra == "optional"
Requires-Dist: biobear; extra == "optional"
Provides-Extra: testing
Requires-Dist: setuptools; extra == "testing"
Requires-Dist: pytest; extra == "testing"
Requires-Dist: pytest-cov; extra == "testing"
Requires-Dist: pandas; extra == "testing"
Requires-Dist: polars; extra == "testing"
Requires-Dist: matplotlib; extra == "testing"
Requires-Dist: joblib; extra == "testing"
Requires-Dist: rich; extra == "testing"
Requires-Dist: seaborn; extra == "testing"
Requires-Dist: biobear; extra == "testing"
Dynamic: license-file
